setup.py
waffle/__init__.py
waffle/app.py
waffle/common.py
waffle/conftest.py
waffle/db.py
waffle/db_test.py
waffle/devel.py
waffle/flags.py
waffle/log.py
waffle/redis.py
waffle.egg-info/PKG-INFO
waffle.egg-info/SOURCES.txt
waffle.egg-info/dependency_links.txt
waffle.egg-info/requires.txt
waffle.egg-info/top_level.txt
waffle/web/__init__.py
waffle/web/clastic.py
waffle/web/common.py
waffle/web/csrf.py
waffle/web/db.py
waffle/web/template.py