Metadata-Version: 1.0
Name: waffle
Version: 0.5.0
Summary: Waffle - A Dependency-Injection-based application framework for Python
Home-page: http://github.com/alecthomas/waffle
Author: Alec Thomas
Author-email: alec@swapoff.org
License: BSD
Download-URL: http://pypi.python.org/pypi/waffle
Platform: any
